trellis/__init__.py
trellis/__version__.py
trellis/plotting.py
trellis/random_processes.py
trellis/utils.py
trellis/models/__init__.py
trellis/models/base.py
trellis/models/utils.py
trellis/models/european_option/__init__.py
trellis/models/european_option/analytics.py
trellis/models/european_option/model.py
trellis/models/variable_annuity/__init__.py
trellis/models/variable_annuity/analytics.py
trellis/models/variable_annuity/model.py
beacon_trellis-0.2.dist-info/LICENSE
beacon_trellis-0.2.dist-info/METADATA
beacon_trellis-0.2.dist-info/WHEEL
beacon_trellis-0.2.dist-info/top_level.txt
beacon_trellis-0.2.dist-info/RECORD
