Metadata-Version: 2.1
Name: beacon-trellis
Version: 0.2
Summary: Trellis is a deep hedging and deep pricing framework for quantitative finance
Home-page: https://github.com/Beacon-Platform/trellis
Author: Benjamin Pryke
Author-email: ben.pryke@beacon.io
Maintainer: Beacon Platform
License: MIT
Project-URL: Maintainer Homepage, https://www.beacon.io
Platform: UNKNOWN
Classifier: Development Status :: 2 - Pre-Alpha
Classifier: Intended Audience :: Developers
Classifier: Intended Audience :: Financial and Insurance Industry
Classifier: Intended Audience :: Science/Research
Classifier: License :: OSI Approved :: MIT License
Classifier: Natural Language :: English
Classifier: Operating System :: OS Independent
Classifier: Programming Language :: Python :: 3 :: Only
Classifier: Programming Language :: Python :: 3.5
Classifier: Programming Language :: Python :: 3.6
Classifier: Programming Language :: Python :: 3.7
Classifier: Programming Language :: Python :: 3.8
Classifier: Programming Language :: Python :: 3
Classifier: Topic :: Scientific/Engineering :: Artificial Intelligence
Classifier: Topic :: Scientific/Engineering :: Mathematics
Classifier: Topic :: Scientific/Engineering
Classifier: Topic :: Software Development :: Libraries :: Python Modules
Classifier: Topic :: Software Development :: Libraries
Classifier: Topic :: Software Development
Requires-Python: >=3.5
Requires-Dist: matplotlib (>=3.0.0)
Requires-Dist: numpy (>=1.16.0)
Requires-Dist: scipy (>=1.4.1)
Requires-Dist: seaborn (>=0.9.0)
Requires-Dist: tensorflow (>=2.4.1)
